data_plumber_http/__init__.py
data_plumber_http/output.py
data_plumber_http/py.typed
data_plumber_http/settings.py
data_plumber_http/decorators/__init__.py
data_plumber_http/decorators/flask_input.py
data_plumber_http/keys/__init__.py
data_plumber_http/keys/all_of.py
data_plumber_http/keys/conditional_key.py
data_plumber_http/keys/one_of.py
data_plumber_http/keys/property.py
data_plumber_http/types/__init__.py
data_plumber_http/types/any.py
data_plumber_http/types/array.py
data_plumber_http/types/boolean.py
data_plumber_http/types/file_system_object.py
data_plumber_http/types/float.py
data_plumber_http/types/integer.py
data_plumber_http/types/null.py
data_plumber_http/types/number.py
data_plumber_http/types/object.py
data_plumber_http/types/string.py
data_plumber_http/types/uri.py
data_plumber_http/types/url.py
data_plumber_http-1.0.1.dist-info/LICENSE
data_plumber_http-1.0.1.dist-info/METADATA
data_plumber_http-1.0.1.dist-info/WHEEL
data_plumber_http-1.0.1.dist-info/top_level.txt
data_plumber_http-1.0.1.dist-info/RECORD
