Metadata-Version: 2.1
Name: data-plumber-http
Version: 1.0.1
Summary: http extension for the data-plumber python framework
Home-page: https://pypi.org/project/data-plumber-http/
Author: Steffen Richters-Finger
Author-email: srichters@uni-muenster.de
License: MIT
Project-URL: Source, https://github.com/RichtersFinger/data-plumber-http
Classifier: Development Status :: 5 - Production/Stable
Classifier: Intended Audience :: Developers
Classifier: Topic :: Software Development :: Libraries
Classifier: License :: OSI Approved :: MIT License
Classifier: Programming Language :: Python :: 3
Classifier: Programming Language :: Python :: 3.10
Classifier: Programming Language :: Python :: 3.11
Classifier: Programming Language :: Python :: 3.12
Classifier: Framework :: Flask
Requires-Python: >=3.10
License-File: LICENSE
Requires-Dist: data-plumber<2,>=1.15.0
